{"image_id": "VP+91vDqqAkz0NPvJiqeQA==", "request_id": "1550525457,cca50185-d77a-4a43-9e78-4cec9c1f8b55", "time_used": 1825, "faces": [{"attributes": {"emotion": {"sadness": 0.001, "neutral": 97.935, "disgust": 0.001, "anger": 0.0, "surprise": 0.0, "fear": 0.0, "happiness": 2.062}, "beauty": {"female_score": 70.515, "male_score": 62.217}, "gender": {"value": "Male"}, "age": {"value": 26}, "mouthstatus": {"close": 100.0, "surgical_mask_or_respirator": 0.0, "open": 0.0, "other_occlusion": 0.0}, "glass": {"value": "None"}, "skinstatus": {"dark_circle": 5.926, "stain": 13.924, "acne": 19.905, "health": 0.765}, "headpose": {"yaw_angle": -1.3932647, "pitch_angle": -2.1723049, "roll_angle": 7.920002}, "blur": {"blurness": {"threshold": 50.0, "value": 0.371}, "motionblur": {"threshold": 50.0, "value": 0.371}, "gaussianblur": {"threshold": 50.0, "value": 0.371}}, "smile": {"threshold": 50.0, "value": 53.705}, "eyestatus": {"left_eye_status": {"normal_glass_eye_open": 0.005, "no_glass_eye_close": 0.0, "occlusion": 0.0, "no_glass_eye_open": 99.995, "normal_glass_eye_close": 0.0, "dark_glasses": 0.0}, "right_eye_status": {"normal_glass_eye_open": 0.004, "no_glass_eye_close": 0.0, "occlusion": 0.002, "no_glass_eye_open": 99.994, "normal_glass_eye_close": 0.0, "dark_glasses": 0.0}}, "facequality": {"threshold": 70.1, "value": 93.909}, "ethnicity": {"value": "WHITE"}, "eyegaze": {"right_eye_gaze": {"position_x_coordinate": 0.501, "vector_z_component": 0.991, "vector_x_component": 0.08, "vector_y_component": -0.105, "position_y_coordinate": 0.423}, "left_eye_gaze": {"position_x_coordinate": 0.459, "vector_z_component": 0.989, "vector_x_component": -0.104, "vector_y_component": -0.103, "position_y_coordinate": 0.436}}}, "face_rectangle": {"width": 527, "top": 641, "left": 1298, "height": 527}, "face_token": "5984b63e4676e42d2d702572e53975d5"}]}